data_filtering/__init__.py
data_filtering/data_handler.py
data_filtering/duplication_handler.py
data_filtering/main_processor.py
data_filtering/quality_checker.py
data_filtering/report_generator.py
data_filtering/config/default_settings.yaml
data_filtering/templates/report_template.html
data_filtering-0.1.21.dist-info/METADATA
data_filtering-0.1.21.dist-info/WHEEL
data_filtering-0.1.21.dist-info/entry_points.txt
data_filtering-0.1.21.dist-info/top_level.txt
data_filtering-0.1.21.dist-info/RECORD
