Metadata-Version: 2.4
Name: data-filtering
Version: 0.1.21
Summary: A library to filter and deduplicate Q&A text datasets from CSV files.
Author-email: JunNyeong Jeong <junnyeong.jeong@selectstar.ai>
Keywords: data filtering,nlp,deduplication,text processing,csv
Classifier: Development Status :: 3 - Alpha
Classifier: Intended Audience :: Developers
Classifier: Intended Audience :: Science/Research
Classifier: License :: OSI Approved :: MIT License
Classifier: Programming Language :: Python :: 3
Classifier: Programming Language :: Python :: 3.8
Classifier: Programming Language :: Python :: 3.9
Classifier: Programming Language :: Python :: 3.10
Classifier: Programming Language :: Python :: 3.11
Classifier: Topic :: Scientific/Engineering :: Artificial Intelligence
Classifier: Topic :: Text Processing :: Filters
Requires-Python: >=3.11
Requires-Dist: pandas>=1.5
Requires-Dist: PyYAML>=6.0
Requires-Dist: langdetect>=1.0.9
Requires-Dist: scikit-learn>=1.0
Requires-Dist: sentence-transformers>=2.2.2
Requires-Dist: Jinja2>=3.0
